odoo/addons/sale_order_transmit_method/README.rst
odoo/addons/sale_order_transmit_method/__init__.py
odoo/addons/sale_order_transmit_method/__manifest__.py
odoo/addons/sale_order_transmit_method/i18n/ca.po
odoo/addons/sale_order_transmit_method/i18n/es.po
odoo/addons/sale_order_transmit_method/i18n/it.po
odoo/addons/sale_order_transmit_method/i18n/sale_order_transmit_method.pot
odoo/addons/sale_order_transmit_method/models/__init__.py
odoo/addons/sale_order_transmit_method/models/sale_order.py
odoo/addons/sale_order_transmit_method/readme/CONTRIBUTORS.md
odoo/addons/sale_order_transmit_method/readme/DESCRIPTION.md
odoo/addons/sale_order_transmit_method/static/description/icon.png
odoo/addons/sale_order_transmit_method/static/description/index.html
odoo/addons/sale_order_transmit_method/tests/__init__.py
odoo/addons/sale_order_transmit_method/tests/test_sale_order.py
odoo/addons/sale_order_transmit_method/views/sale_order.xml
odoo_addon_sale_order_transmit_method-18.0.1.0.0.4.dist-info/METADATA
odoo_addon_sale_order_transmit_method-18.0.1.0.0.4.dist-info/WHEEL
odoo_addon_sale_order_transmit_method-18.0.1.0.0.4.dist-info/top_level.txt
odoo_addon_sale_order_transmit_method-18.0.1.0.0.4.dist-info/RECORD
